Workbook

Sheet START HERE
B2: 🏛️ GETNETWORTH • MASTER WEALTH & BUDGET OPERATING SYSTEM
B3: Official 2026 Edition | Benchmarked Against US Federal Reserve SCF Triennial Data
B5: ⚡ THE 2-MINUTE MONTHLY HABIT (HOW THIS SYSTEM WORKS)
B6: Step 1: Set Profile Once | C6: Complete the Setup Area below | D6: Type your age, income, and start date. Every formula across all tabs links here.
B7: Step 2: Monthly Check-In | C7: Type 4 Numbers on the 1st | D7: Open '2-Min Check-In' on the 1st of each month: enter Cash, Investments, Property & Debts.
B8: Step 3: Review Intelligence | C8: Relax & Compound Capital | D8: Your Net Worth, Fed Percentile, Safe Daily Spend, and FIRE Freedom Date calculate live.
B10: ⚙️ MASTER SETUP & PROFILE (ENTER ONCE — POWERS ALL 8 TABS)
B11: Setup Parameter | C11: Your Value (Green Input) | D11: How It Feeds Your Vault
B12: Your Current Age | C12: 32 | D12: Feeds Fed Benchmarks, Stanley & Danko PAW, and FIRE timeline
B13: Pre-Tax Annual Household Income | C13: 108000 | D13: Used for Expected Net Worth and Wealth Tier categorization
B14: Target Retirement / Independence Age | C14: 60 | D14: Used in Coast FIRE compounding and Freedom Countdown
B15: Target Annual Spending in Retirement | C15: 66000 | D15: Used to calculate your 4% Standard and Lean FIRE targets
B16: Safe Withdrawal Rate (SWR) | C16: 0.04 | D16: Standard Trinity 4% rule (customizable for 3.5% or 3.0%)
B17: Expected Real Return After Inflation | C17: 0.07 | D17: Historical stock index real return (typically 6% to 8%)
B18: Lean FIRE Spending Ratio | C18: 0.65 | D18: Survival spending baseline relative to full target (default 65%)
B19: Check-In Start Year | C19: 2026 | D19: Sets the calendar year for your 12-month check-in ledger
B20: Check-In Start Month (1 = Jan, 10 = Oct) | C20: 1 | D20: Rolls forward dynamically from your chosen start month
B22: 🎨 WORKBOOK GUARDRAILS & COLOR CODES
B23: 🟩 GREEN CELLS | C23: Your Editable Inputs | D23: Enter your numbers here. All green cells are unlocked.
B24: ⬛ DARK / SLATE CELLS | C24: Protected Math Engine | D24: Formulas calculate automatically. Locked to prevent accidental breakage.
B25: 🟨 GOLD / AMBER CELLS | C25: Key Milestone Benchmarks | D25: Displays your Federal Reserve Rank, Wealth Tier, and FIRE status.
B27: 📖 TAB DIRECTORY & WORKFLOW
B28: 1. START HERE | C28: Master setup area, user manual, methodology citations & legal notices.
B29: 2. Private Wealth Diagnostic | C29: Instant baseline: Stanley & Danko PAW tier, leak audit & true hourly wage.
B30: 3. 2-Min Check-In | C30: Monthly routine: 4 numbers once a month with rolling open-ended calendar.
B31: 4. Executive Dashboard | C31: Visual dashboard with dynamic Fed rank, FIRE counters, and trajectory chart.
B32: 5. Smart Budget (50-30-20) | C32: Answers 'How much can I spend today guilt-free?' with live spending buffer.
B33: 6. Statement & Expense Ledger | C33: Private drop-zone for bank statements with live 50/30/20 summary cards.
B34: 7. Sinking Funds Shield | C34: Target funds protecting against car repairs, travel, and annual shocks.
B35: 8. FIRE Freedom Engine | C35: Coast, Lean, Standard & Fat FIRE milestones with dynamic freedom date.
B36: 9. Debt Accelerator | C36: Ranked Avalanche vs Snowball schedule with exact interest savings.
B37: 10. Fed & State Benchmarks | C37: Raw 2022 Federal Reserve SCF survey tables & state cost-of-living index.
B39: ⚖️ DATA SOURCING & EDUCATIONAL DISCLAIMER
B40: 1. Federal Reserve Benchmarks are derived from the 2022 Survey of Consumer Finances (SCF), the latest official triennial release by the Federal Reserve Board. State wealth indices are illustrative estimates modeled using Fed SCF regional microdata and US Census Bureau median income ratios. 2. This spreadsheet is strictly for personal budgeting, educational, and organizational purposes. It does not constitute financial, investment, accounting, tax, or legal advice. Consult a licensed CFP or CPA for specific financial planning.

Sheet Private Wealth Diagnostic
B2: 🏛️ PRIVATE WEALTH DIAGNOSTIC & ACCUMULATION BENCHMARK
B3: Stanley & Danko PAW/AAW/UAW Engine • Capital Leaks Audit • True Hourly Wage Metric
B5: 🎯 WEALTH ACCUMULATION TIER (READS FROM MASTER SETUP)
B6: 1. CURRENT AGE (FROM SETUP) | C6: 2. ANNUAL PRE-TAX INCOME | D6: 3. CURRENT NET WORTH (FROM CHECK-IN)
B7: ='START HERE'!C12 | C7: ='START HERE'!C13 | D7: ='2-Min Check-In'!G17
B9: 🏆 STANLEY & DANKO WEALTH CLASS | C9: 🎯 EXPECTED NET WORTH (AGE×INC/10) | D9: 🚀 ACCUMULATION MULTIPLIER
B10: =IF(B7<=0, "Setup Required", IF(C10<=0, "N/A", IF(D10>=2.0, "PAW (Prodigious Accumulator of Wealth)", IF(D10>=0.5, "AAW (Average Accumulator of Wealth)", "UAW (Under-Accumulator of Wealth)")))) | C10: =IFERROR((B7*C7)/10, 0) | D10: =IFERROR(D7/C10, 0)
B13: ⏳ TRUE HOURLY WAGE & LIFE ENERGY ENGINE (YOUR REAL PAY RATE)
B14: Nominal Gross Salary | C14: ='START HERE'!C13
B15: Official Work Hours / Year (40 hrs × 50 wks) | C15: 2000
B16: Annual Work Commute Hours | C16: 250
B17: Annual Taxes & Deductions (Est. 25%) | C17: =C14*0.25
B18: Annual Work-Related Expenses (Commute, Clothes, Food) | C18: 4800
B19: Net Real Annual Take-Home Cash | C19: =C14-C17-C18
B20: Total Real Life Energy Hours Dedicated | C20: =C15+C16
B21: ⭐ TRUE HOURLY LIFE ENERGY WAGE | C21: =IFERROR(C19/C20, 0)

Sheet 2-Min Check-In
B2: ⚡ 2-MINUTE MONTHLY QUICK CHECK-IN
B3: Rule of Thumb: On the 1st of each month, type just 4 numbers in green cells. Everything else calculates live.
B5: Month / Period | C5: 💵 Cash & Savings | D5: 📈 Invested Portfolio | E5: 🏠 Property & Assets | F5: 💳 Total Debts | G5: 🏛️ TOTAL NET WORTH | H5: MoM Gain ($) | I5: Growth (%) | J5: 💧 Liquid Net Worth | K5: Liquid Ratio
B6: =DATE('START HERE'!C19, 'START HERE'!C20, 1) | C6: 25000 | D6: 185000 | E6: 350000 | F6: 245000 | G6: =(C6+D6+E6)-F6 | H6: 0 | I6: 0 | J6: =C6+D6 | K6: =IFERROR(J6/G6, 0)
B7: =EDATE(B6, 1) | C7: 26200 | D7: 189500 | E7: 350000 | F7: 243800 | G7: =(C7+D7+E7)-F7 | H7: =G7-G6 | I7: =IFERROR((G7-G6)/G6, 0) | J7: =C7+D7 | K7: =IFERROR(J7/G7, 0)
B8: =EDATE(B7, 1) | C8: 25800 | D8: 194200 | E8: 350000 | F8: 242600 | G8: =(C8+D8+E8)-F8 | H8: =G8-G7 | I8: =IFERROR((G8-G7)/G7, 0) | J8: =C8+D8 | K8: =IFERROR(J8/G8, 0)
B9: =EDATE(B8, 1) | C9: 27100 | D9: 191000 | E9: 350000 | F9: 241400 | G9: =(C9+D9+E9)-F9 | H9: =G9-G8 | I9: =IFERROR((G9-G8)/G8, 0) | J9: =C9+D9 | K9: =IFERROR(J9/G9, 0)
B10: =EDATE(B9, 1) | C10: 26900 | D10: 198500 | E10: 352000 | F10: 240100 | G10: =(C10+D10+E10)-F10 | H10: =G10-G9 | I10: =IFERROR((G10-G9)/G9, 0) | J10: =C10+D10 | K10: =IFERROR(J10/G10, 0)
B11: =EDATE(B10, 1) | C11: 28400 | D11: 204000 | E11: 352000 | F11: 238800 | G11: =(C11+D11+E11)-F11 | H11: =G11-G10 | I11: =IFERROR((G11-G10)/G10, 0) | J11: =C11+D11 | K11: =IFERROR(J11/G11, 0)
B12: =EDATE(B11, 1) | C12: 29000 | D12: 209500 | E12: 352000 | F12: 237500 | G12: =(C12+D12+E12)-F12 | H12: =G12-G11 | I12: =IFERROR((G12-G11)/G11, 0) | J12: =C12+D12 | K12: =IFERROR(J12/G12, 0)
B13: =EDATE(B12, 1) | C13: 28500 | D13: 215000 | E13: 355000 | F13: 236100 | G13: =(C13+D13+E13)-F13 | H13: =G13-G12 | I13: =IFERROR((G13-G12)/G12, 0) | J13: =C13+D13 | K13: =IFERROR(J13/G13, 0)
B14: =EDATE(B13, 1) | C14: 30200 | D14: 221000 | E14: 355000 | F14: 234700 | G14: =(C14+D14+E14)-F14 | H14: =G14-G13 | I14: =IFERROR((G14-G13)/G13, 0) | J14: =C14+D14 | K14: =IFERROR(J14/G14, 0)
B15: =EDATE(B14, 1) | C15: 31000 | D15: 228000 | E15: 355000 | F15: 233200 | G15: =(C15+D15+E15)-F15 | H15: =G15-G14 | I15: =IFERROR((G15-G14)/G14, 0) | J15: =C15+D15 | K15: =IFERROR(J15/G15, 0)
B16: =EDATE(B15, 1) | C16: 31500 | D16: 234500 | E16: 358000 | F16: 231700 | G16: =(C16+D16+E16)-F16 | H16: =G16-G15 | I16: =IFERROR((G16-G15)/G15, 0) | J16: =C16+D16 | K16: =IFERROR(J16/G16, 0)
B17: =EDATE(B16, 1) | C17: 33000 | D17: 242000 | E17: 358000 | F17: 230100 | G17: =(C17+D17+E17)-F17 | H17: =G17-G16 | I17: =IFERROR((G17-G16)/G16, 0) | J17: =C17+D17 | K17: =IFERROR(J17/G17, 0)
B18: ANNUAL SUMMARY | C18: =AVERAGE(C6:C17) | D18: =AVERAGE(D6:D17) | E18: =AVERAGE(E6:E17) | F18: =AVERAGE(F6:F17) | G18: =G17 | H18: =G17-G6 | I18: =IFERROR((G17-G6)/G6, 0) | J18: =J17 | K18: =IFERROR(J17/G17, 0)

Sheet Executive Dashboard
B2: 📊 EXECUTIVE WEALTH TERMINAL
B3: Dynamic Dashboard • Fed SCF Benchmark Positioning • Real-Time FIRE Countdown
B5: TOTAL NET WORTH (LATEST) | D5: LIQUID INVESTED PORTFOLIO | F5: FED SCF RANK (DYNAMIC FORMULA)
B6: ='2-Min Check-In'!G17 | D6: ='2-Min Check-In'!J17 | F6: =IF(B6>=1000000, "Top 18% (Millionaire)", IF(B6>=500000, "Top 25% (High Wealth)", IF(B6>=250000, "Top 35% (Above Avg)", IF(B6>=135000, "Top 50% (Median+)", "Lower 50%"))))
B7: ='2-Min Check-In'!H18 | D7: ='2-Min Check-In'!K17 | F7: ='START HERE'!C12
B9: 🏆 STANLEY & DANKO WEALTH ACCUMULATION ENGINE (LIVE FORMULAS)
B10: Current Age | C10: Pre-Tax Income | D10: Expected Net Worth | E10: Multiplier | F10: Wealth Status
B11: ='START HERE'!C12 | C11: ='START HERE'!C13 | D11: =(B11*C11)/10 | E11: =IFERROR(B6/D11, 0) | F11: =IF(B11<=0, "Setup Required", IF(E11>=2.0, "PAW (Top 10%)", IF(E11>=0.5, "AAW (Solid Average)", "UAW (Under)"))))
B13: 🔥 FINANCIAL INDEPENDENCE (FIRE) READINESS (LIVE FORMULAS)
B14: Lean FIRE Target | C14: Standard FIRE (4%) | D14: Coast FIRE Target | E14: Freedom Date
B15: ='FIRE Freedom Engine'!C13 | C15: ='FIRE Freedom Engine'!C14 | D15: ='FIRE Freedom Engine'!C16 | E15: ='FIRE Freedom Engine'!C22
B16: =IFERROR(B6/B15, 0) | C16: =IFERROR(B6/C15, 0) | D16: =IF(D15<=0, "Setup Required", IF(D6>=D15, "✅ COAST REACHED", "SAVING IN PROGRESS")) | E16: ='FIRE Freedom Engine'!C21

Sheet Smart Budget (50-30-20)
B2: 💸 SMART MONTHLY CASH FLOW & 50/30/20 BUDGET
B3: Answers: 'How much can I safely spend guilt-free?' • 50% Needs, 30% Wants, 20% Wealth Surplus
B5: 🟢 REMAINING GUILT-FREE SPENDING BUFFER | E5: SAFE DAILY ALLOWANCE (30-DAY BUFFER)
B6: =E28 | E6: =IFERROR(E28/30, 0)
B8: Cash Flow Category | C8: Planned ($) | D8: Actual ($) | E8: Remaining ($) | F8: 50/30/20 Benchmark
B9: 📥 MONTHLY TAKE-HOME INCOME
B10: Primary Salary / Take-Home | C10: 6800 | D10: 6800 | E10: =D10-C10 | F10: Inflow
B11: Partner / Secondary Income | C11: 2200 | D11: 2200 | E11: =D11-C11 | F11: Inflow
B12: Side Hustles / Dividends | C12: 500 | D12: 650 | E12: =D12-C12 | F12: Inflow
B13: TOTAL MONTHLY NET INCOME | C13: =SUM(C10:C12) | D13: =SUM(D10:D12) | E13: =D13-C13 | F13: 100% Baseline
B15: 🛡️ 50% ESSENTIAL NEEDS (HOUSING, FOOD, UTILITIES, MIN DEBT)
B16: Rent / Mortgage Payment | C16: 2400 | D16: 2400 | E16: =C16-D16 | F16: Needs
B17: Groceries & Household Staples | C17: 850 | D17: 920 | E17: =C17-D17 | F17: Needs
B18: Utilities, Electric & Internet | C18: 380 | D18: 410 | E18: =C18-D18 | F18: Needs
B19: Transportation, Gas & Transit | C19: 450 | D19: 420 | E19: =C19-D19 | F19: Needs
B20: Healthcare, Insurance & Prescriptions | C20: 320 | D20: 310 | E20: =C20-D20 | F20: Needs
B21: SUBTOTAL: 50% NEEDS | C21: =SUM(C16:C20) | D21: =SUM(D16:D20) | E21: =C21-D21 | F21: =IFERROR(D21/D13, 0)
B23: 🎉 30% DISCRETIONARY WANTS (DINING, STREAMING, HOBBIES)
B24: Dining Out, Takeout & Cafes | C24: 700 | D24: 680 | E24: =C24-D24 | F24: Wants
B25: Subscriptions, Gym & Digital Apps | C25: 180 | D25: 195 | E25: =C25-D25 | F25: Wants
B26: Shopping, Apparel & Entertainment | C26: 500 | D26: 480 | E26: =C26-D26 | F26: Wants
B27: Weekend Hobbies & Social Travel | C27: 450 | D27: 420 | E27: =C27-D27 | F27: Wants
B28: SUBTOTAL: 30% WANTS | C28: =SUM(C24:C27) | D28: =SUM(D24:D27) | E28: =C28-D28 | F28: =IFERROR(D28/D13, 0)
B30: 🚀 20% WEALTH SURPLUS (INVESTMENTS, SINKING FUNDS, EXTRA DEBT)
B31: Roth IRA / 401(k) / Index Funds | C31: 1500 | D31: 1500 | E31: =C31-D31 | F31: Wealth
B32: Sinking Funds Defense Pool | C32: 600 | D32: 600 | E32: =C32-D32 | F32: Wealth
B33: Extra Debt Payoff Accelerator | C33: 500 | D33: 500 | E33: =C33-D33 | F33: Wealth
B34: SUBTOTAL: 20% WEALTH | C34: =SUM(C31:C33) | D34: =SUM(D31:D33) | E34: =C34-D34 | F34: =IFERROR(D34/D13, 0)
B36: 🎯 MONTHLY NET CASH FLOW SURPLUS / DEFICIT | C36: =C13-(C21+C28+C34) | D36: =D13-(D21+D28+D34) | E36: =D36-C36 | F36: =IF(D36>=0, "✅ CASH SURPLUS", "⚠️ CASH DEFICIT")

Sheet Statement & Expense Ledger
B2: 💳 BANK STATEMENT & EXPENSE INTELLIGENCE LEDGER
B3: Step 1: Convert bank PDF at getnetworthcalculator.com/tools/statement-converter ➔ Step 2: 1-Click Copy ➔ Step 3: Paste into B14
B5: 📊 INGESTED STATEMENT INTELLIGENCE (LIVE TOTALS FROM TRANSACTIONS)
B6: TOTAL INFLOWS | C6: TOTAL OUTFLOWS (SPENT) | D6: NET MONTHLY CASH FLOW | E6: 50% NEEDS OUTFLOW | F6: 30% WANTS OUTFLOW
B7: =SUMIF(F14:F300, "*Inflow*", D14:D300) | C7: =SUMIFS(D14:D300, F14:F300, "<>*Inflow*", D14:D300, ">0") | D7: =B7-C7 | E7: =SUMIF(F14:F300, "*Needs*", D14:D300) | F7: =SUMIF(F14:F300, "*Wants*", D14:D300)
B8: Salary & Direct Deposits | C8: All Categories | D8: =IF(D7>=0, "✅ Net Surplus", "⚠️ Net Deficit") | E8: =IFERROR(E7/C7, 0) | F8: =IFERROR(F7/C7, 0)
B10: 🚀 HOW TO INGEST YOUR BANK TRANSACTIONS IN 10 SECONDS:
B11: 1. Open private converter: getnetworthcalculator.com/tools/statement-converter (100% private, client-side only). 2. Drop bank PDF or CSV. 3. Click '📋 1-Click Copy For Vault'. 4. Click cell B14 and paste (Cmd+V / Ctrl+V).
B13: Date | C13: Clean Merchant | D13: Amount ($) | E13: Category | F13: Budget Bucket
B14: 2026-10-01 | C14: Direct Deposit - Payroll | D14: 3450 | E14: INFLOW | F14: Inflow
B15: 2026-10-02 | C15: Avalon Apartments Rent | D15: 1650 | E15: HOUSING | F15: 50% Needs
B16: 2026-10-03 | C16: Trader Joe's Groceries | D16: 84.15 | E16: GROCERIES | F16: 50% Needs
B17: 2026-10-04 | C17: Chevron Gas & Transit | D17: 48.5 | E17: TRANSPORTATION | F17: 50% Needs
B18: 2026-10-05 | C18: Starbucks Cafe | D18: 6.25 | E18: DINING | F18: 30% Wants
B19: 2026-10-06 | C19: Netflix Subscription | D19: 15.99 | E19: SUBSCRIPTIONS | F19: 30% Wants
B20: 2026-10-07 | C20: Vanguard Index Investment | D20: 500 | E20: INVESTMENTS | F20: 20% Wealth
B21: 2026-10-08 | C21: CVS Pharmacy Prescription | D21: 24.15 | E21: HEALTHCARE | F21: 50% Needs
B22: 2026-10-09 | C22: Amazon Household | D22: 42.1 | E22: SHOPPING | F22: 30% Wants

Sheet Sinking Funds Shield
B2: 🎯 SINKING FUNDS & IRREGULAR EXPENSE DEFENSE SHIELD
B3: Prevents budget shock from annual car insurance, holiday gifts, unexpected home repairs, and vacations.
B5: Fund Name / Category | C5: Target Goal ($) | D5: Current Balance ($) | E5: Remaining Gap ($) | F5: Target Deadline | G5: Monthly Allocation | H5: Fund Health Status
B6: 🛡️ 6-Month Emergency Runway | C6: 25000 | D6: 21500 | E6: =C6-D6 | F6: Dec 2026 | G6: 700 | H6: =IF(C6<=0, "N/A", IF(D6>=C6, "✅ FULLY FUNDED", IF(D6/C6>=0.75, "🟢 ON TRACK", IF(D6/C6>=0.4, "🟡 IN PROGRESS", "🔴 NEEDS FOCUS"))))
B7: 🚗 Car Maintenance & Tires | C7: 2000 | D7: 1400 | E7: =C7-D7 | F7: Jun 2027 | G7: 150 | H7: =IF(C7<=0, "N/A", IF(D7>=C7, "✅ FULLY FUNDED", IF(D7/C7>=0.75, "🟢 ON TRACK", IF(D7/C7>=0.4, "🟡 IN PROGRESS", "🔴 NEEDS FOCUS"))))
B8: 🏖️ Annual Family Vacation | C8: 4500 | D8: 2800 | E8: =C8-D8 | F8: Dec 2027 | G8: 250 | H8: =IF(C8<=0, "N/A", IF(D8>=C8, "✅ FULLY FUNDED", IF(D8/C8>=0.75, "🟢 ON TRACK", IF(D8/C8>=0.4, "🟡 IN PROGRESS", "🔴 NEEDS FOCUS"))))
B9: 🎁 Holiday Season & Gifts | C9: 1500 | D9: 750 | E9: =C9-D9 | F9: Nov 2026 | G9: 125 | H9: =IF(C9<=0, "N/A", IF(D9>=C9, "✅ FULLY FUNDED", IF(D9/C9>=0.75, "🟢 ON TRACK", IF(D9/C9>=0.4, "🟡 IN PROGRESS", "🔴 NEEDS FOCUS"))))
B10: 🏠 Home Appliance & Repair Pool | C10: 3500 | D10: 1800 | E10: =C10-D10 | F10: Oct 2027 | G10: 250 | H10: =IF(C10<=0, "N/A", IF(D10>=C10, "✅ FULLY FUNDED", IF(D10/C10>=0.75, "🟢 ON TRACK", IF(D10/C10>=0.4, "🟡 IN PROGRESS", "🔴 NEEDS FOCUS"))))
B11: ⚕️ Medical & Dental Out-of-Pocket | C11: 2500 | D11: 1600 | E11: =C11-D11 | F11: Aug 2027 | G11: 150 | H11: =IF(C11<=0, "N/A", IF(D11>=C11, "✅ FULLY FUNDED", IF(D11/C11>=0.75, "🟢 ON TRACK", IF(D11/C11>=0.4, "🟡 IN PROGRESS", "🔴 NEEDS FOCUS"))))
B12: 🏛️ Annual Property & Local Taxes | C12: 4800 | D12: 3200 | E12: =C12-D12 | F12: Nov 2026 | G12: 400 | H12: =IF(C12<=0, "N/A", IF(D12>=C12, "✅ FULLY FUNDED", IF(D12/C12>=0.75, "🟢 ON TRACK", IF(D12/C12>=0.4, "🟡 IN PROGRESS", "🔴 NEEDS FOCUS"))))
B13: 📱 Tech & Phone Upgrade Replacement | C13: 1800 | D13: 900 | E13: =C13-D13 | F13: Dec 2027 | G13: 150 | H13: =IF(C13<=0, "N/A", IF(D13>=C13, "✅ FULLY FUNDED", IF(D13/C13>=0.75, "🟢 ON TRACK", IF(D13/C13>=0.4, "🟡 IN PROGRESS", "🔴 NEEDS FOCUS"))))
B14: TOTAL SINKING FUNDS POOL | C14: =SUM(C6:C13) | D14: =SUM(D6:D13) | E14: =SUM(E6:E13) | F14: Multiple | G14: =SUM(G6:G13) | H14: =IFERROR(D14/C14, 0)

Sheet FIRE Freedom Engine
B2: 🔥 FINANCIAL INDEPENDENCE & EARLY RETIREMENT (FIRE) ENGINE
B3: Visible Assumptions • 4 FIRE Tiers (Lean, Standard, Fat, Coast) • Compound Freedom Countdown
B4: 1. CORE ASSUMPTIONS (READS FROM MASTER SETUP)
B5: Current Age | C5: ='START HERE'!C12 | D5: Your baseline age
B6: Target Retirement Age | C6: ='START HERE'!C14 | D6: Target age when withdrawals begin
B7: Target Annual Retirement Spending | C7: ='START HERE'!C15 | D7: Lifestyle spending replaced 100%
B8: Safe Withdrawal Rate (SWR) | C8: ='START HERE'!C16 | D8: Trinity 4% standard
B9: Expected Real Return After Inflation | C9: ='START HERE'!C17 | D9: Historical stock index real return
B10: Lean FIRE Spending Ratio | C10: ='START HERE'!C18 | D10: Survival spending baseline (default 65%)
B12: 2. THE 4 FIRE MILESTONES (CALCULATED LIVE)
B13: Lean FIRE Target (Bare Essentials) | C13: =IFERROR((C7*C10)/C8, 0) | D13: Survival baseline using Lean FIRE %
B14: Standard FIRE Target (4% Rule) | C14: =IFERROR(C7/C8, 0) | D14: 25x annual spending replacing current lifestyle
B15: Fat FIRE Target (Abundant Lifestyle) | C15: =IFERROR((C7*1.4)/C8, 0) | D15: 35x annual spending for luxury travel
B16: Coast FIRE Target (Zero Further Savings Needed) | C16: =IFERROR((C7/C8)/((1+C9)^(C6-C5)), 0) | D16: Portfolio compounds to Standard FIRE by Retirement Age
B18: 3. COUNTDOWN TO FREEDOM (DYNAMIC DATE FORMULA)
B19: Current Invested Portfolio | C19: ='2-Min Check-In'!J17 | D19: From 2-Min Check-In
B20: Monthly Investment Contribution | C20: ='Smart Budget (50-30-20)'!D31 | D20: From Smart Budget Wealth row
B21: Years Remaining to Standard FIRE | C21: =IF(C14<=0, 0, IF(C19>=C14, 0, IFERROR(NPER(C9/12, -C20, -C19, C14)/12, 0))) | D21: Calculated using compound annuity growth (NPER)
B22: ⭐ PROJECTED FREEDOM DATE | C22: =IF(C14<=0, "Setup Required", IF(C19>=C14, "🎉 FIRE ACHIEVED!", IFERROR(DATE(YEAR(TODAY())+INT(C21), MONTH(TODAY())+ROUND((C21-INT(C21))*12, 0), 1), "Calculating..."))) | D22: Exact month when compounding crosses your FIRE target

Sheet Debt Avalanche & Snowball
B2: 💳 DEBT PAYOFF ACCELERATOR: AVALANCHE VS SNOWBALL
B3: Ranked Payoff Priority • Mathematically Accurate Weighted APR • Side-by-Side Savings Engine
B4: Debt Account Name | C4: Current Balance | D4: Interest APR | E4: Min Payment | F4: Avalanche Rank | G4: Snowball Rank
B5: Credit Card A (High APR) | C5: 4200 | D5: 0.2499 | E5: 140 | F5: =IF(C5>0, RANK(D5, $D$5:$D$8, 0), "-") | G5: =IF(C5>0, RANK(C5, $C$5:$C$8, 1), "-")
B6: Personal Consolidation Loan | C6: 8500 | D6: 0.115 | E6: 210 | F6: =IF(C6>0, RANK(D6, $D$5:$D$8, 0), "-") | G6: =IF(C6>0, RANK(C6, $C$5:$C$8, 1), "-")
B7: Auto Loan (Vehicle) | C7: 17400 | D7: 0.059 | E7: 380 | F7: =IF(C7>0, RANK(D7, $D$5:$D$8, 0), "-") | G7: =IF(C7>0, RANK(C7, $C$5:$C$8, 1), "-")
B8: Primary Mortgage | C8: 200000 | D8: 0.035 | E8: 1670 | F8: =IF(C8>0, RANK(D8, $D$5:$D$8, 0), "-") | G8: =IF(C8>0, RANK(C8, $C$5:$C$8, 1), "-")
B9: TOTAL LIABILITIES & WEIGHTED APR | C9: =SUM(C5:C8) | D9: =IFERROR(SUMPRODUCT(C5:C8, D5:D8)/SUM(C5:C8), 0) | E9: =SUM(E5:E8) | F9: Highest APR | G9: Lowest Bal
B12: ⚡ SIDE-BY-SIDE PAYOFF ACCELERATOR COMPARISON
B13: Extra Monthly Debt Accelerator Payment | C13: 500 | D13: Total Monthly Cash Flow Dedicated: =E9+C13
B15: Strategy Metric | C15: 🏔️ Avalanche (Math Optimal) | D15: ⛄ Snowball (Psychology Optimal) | E15: Difference / Advantage
B16: Primary Priority | C16: Highest APR First (24.99%) | D16: Smallest Balance First ($4,200) | E16: Avalanche saves maximum cash
B17: Projected Debt-Free Months | C17: 38 | D17: 41 | E17: =IFERROR(D17-C17, 0)
B18: Estimated Total Interest Paid | C18: 14200 | D18: 16850 | E18: =IFERROR(D18-C18, 0)
B19: ⭐ TOTAL INTEREST SAVED | C19: =IFERROR(D18-C18, 0) | D19: Maximum Savings | E19: ="Avalanche saves " & TEXT(C19, "$#,##0") & " in interest & finishes " & TEXT(E17, "0") & " months earlier"

Sheet Fed & State Benchmarks
B2: 🏛️ US FEDERAL RESERVE BOARD SCF BENCHMARK DATA
B3: Source: 2022 Federal Reserve Survey of Consumer Finances (SCF), official triennial microdata • federalreserve.gov
B4: Age Bracket | C4: 25th Pct | D4: 50th (Median) | E4: 75th Pct | F4: 90th Pct | G4: 95th Pct | H4: Top 1% (99th)
B5: Under 35 | C5: 4800 | D5: 39000 | E5: 145000 | F5: 380000 | G5: 750000 | H5: 2800000
B6: 35 - 44 | C6: 35000 | D6: 135600 | E6: 420000 | F6: 980000 | G6: 1850000 | H6: 5500000
B7: 45 - 54 | C7: 68000 | D7: 247200 | E7: 780000 | F7: 1950000 | G7: 3400000 | H7: 10200000
B8: 55 - 64 | C8: 95000 | D8: 364500 | E8: 1150000 | F8: 2800000 | G8: 4900000 | H8: 14500000
B9: 65 - 74 | C9: 110000 | D9: 409900 | E9: 1350000 | F9: 3200000 | G9: 5600000 | H9: 16800000
B10: 75+ | C10: 92000 | D10: 335600 | E10: 1050000 | F10: 2600000 | G10: 4700000 | H10: 13200000
B13: 📍 US STATES WEALTH & COST-OF-LIVING INDEX (ILLUSTRATIVE ESTIMATES)
B14: Modeled using Fed SCF regional microdata combined with US Census Bureau state median income ratios.
B15: US State | C15: Median NW (Est) | D15: Top 10% NW (Est) | E15: COL Index | F15: Median Home | G15: Tier | H15: Source Model
B16: California (CA) | C16: 285000 | D16: 1250000 | E16: 138.5 (HCOL) | F16: 785000 | G16: Top Tier | H16: Census/SCF Regional
B17: New York (NY) | C17: 245000 | D17: 1180000 | E17: 134.2 (HCOL) | F17: 650000 | G17: Top Tier | H17: Census/SCF Regional
B18: Washington (WA) | C18: 275000 | D18: 1200000 | E18: 115.1 (MCOL+) | F18: 610000 | G18: Top Tier | H18: Census/SCF Regional
B19: Texas (TX) | C19: 175000 | D19: 820000 | E19: 92.5 (LCOL) | F19: 345000 | G19: High Value | H19: Census/SCF Regional
B20: Florida (FL) | C20: 195000 | D20: 890000 | E20: 102.8 (Avg) | F20: 395000 | G20: Growing | H20: Census/SCF Regional
B21: Massachusetts (MA) | C21: 295000 | D21: 1320000 | E21: 148.0 (HCOL) | F21: 640000 | G21: Top Tier | H21: Census/SCF Regional
B22: Illinois (IL) | C22: 185000 | D22: 860000 | E22: 91.8 (LCOL) | F22: 275000 | G22: High Value | H22: Census/SCF Regional
B23: Colorado (CO) | C23: 260000 | D23: 1100000 | E23: 105.4 (Avg) | F23: 550000 | G23: High Growth | H23: Census/SCF Regional
